fastdtlmapper/__init__.py
fastdtlmapper/angst/__init__.py
fastdtlmapper/angst/event_map.py
fastdtlmapper/angst/model/__init__.py
fastdtlmapper/angst/model/node_event.py
fastdtlmapper/angst/model/transfer.py
fastdtlmapper/angst/transfer_gene.py
fastdtlmapper/args.py
fastdtlmapper/bin/AnGST_wrapper.py
fastdtlmapper/bin/OrthoFinder/License.md
fastdtlmapper/bin/OrthoFinder/README.md
fastdtlmapper/bin/OrthoFinder/orthofinder.py
fastdtlmapper/bin/OrthoFinder/scripts_of/__init__.py
fastdtlmapper/bin/OrthoFinder/scripts_of/__main__.py
fastdtlmapper/bin/OrthoFinder/scripts_of/bin/diamond
fastdtlmapper/bin/OrthoFinder/scripts_of/bin/fastme
fastdtlmapper/bin/OrthoFinder/scripts_of/bin/mcl
fastdtlmapper/bin/OrthoFinder/scripts_of/blast_file_processor.py
fastdtlmapper/bin/OrthoFinder/scripts_of/config.json
fastdtlmapper/bin/OrthoFinder/scripts_of/consensus_tree.py
fastdtlmapper/bin/OrthoFinder/scripts_of/files.py
fastdtlmapper/bin/OrthoFinder/scripts_of/matrices.py
fastdtlmapper/bin/OrthoFinder/scripts_of/mcl.py
fastdtlmapper/bin/OrthoFinder/scripts_of/newick.py
fastdtlmapper/bin/OrthoFinder/scripts_of/orthologues.py
fastdtlmapper/bin/OrthoFinder/scripts_of/parallel_task_manager.py
fastdtlmapper/bin/OrthoFinder/scripts_of/probroot.py
fastdtlmapper/bin/OrthoFinder/scripts_of/program_caller.py
fastdtlmapper/bin/OrthoFinder/scripts_of/resolve.py
fastdtlmapper/bin/OrthoFinder/scripts_of/stag.py
fastdtlmapper/bin/OrthoFinder/scripts_of/stride.py
fastdtlmapper/bin/OrthoFinder/scripts_of/tree.py
fastdtlmapper/bin/OrthoFinder/scripts_of/trees2ologs_dlcpar.py
fastdtlmapper/bin/OrthoFinder/scripts_of/trees2ologs_of.py
fastdtlmapper/bin/OrthoFinder/scripts_of/trees_msa.py
fastdtlmapper/bin/OrthoFinder/scripts_of/trim.py
fastdtlmapper/bin/OrthoFinder/scripts_of/util.py
fastdtlmapper/bin/OrthoFinder/scripts_of/wrapper_phyldog.py
fastdtlmapper/bin/OrthoFinder/tools/__init__.py
fastdtlmapper/bin/OrthoFinder/tools/convert_orthofinder_tree_ids.py
fastdtlmapper-0.3.4.dist-info/entry_points.txt
fastdtlmapper-0.3.4.dist-info/LICENSE
fastdtlmapper-0.3.4.dist-info/WHEEL
fastdtlmapper-0.3.4.dist-info/METADATA
fastdtlmapper-0.3.4.dist-info/RECORD
