Metadata-Version: 2.1
Name: fastdtlmapper
Version: 0.3.4
Summary: Fast genome-wide DTL(Duplication-Transfer-Loss) event mapping tool
Home-page: https://github.com/moshi4/FastDTLmapper/
License: GPL-3.0-only
Keywords: fastdtlmapper,bioinformatics,genomics,phylogenetics,phylogenomics
Author: moshi
Requires-Python: >=3.7.1,<3.10
Classifier: Intended Audience :: Science/Research
Classifier: License :: OSI Approved :: GNU General Public License v3 (GPLv3)
Classifier: Operating System :: POSIX :: Linux
Classifier: Programming Language :: Python :: 3
Classifier: Programming Language :: Python :: 3.8
Classifier: Programming Language :: Python :: 3.9
Classifier: Topic :: Scientific/Engineering :: Bio-Informatics
Requires-Dist: PyQt5 (>=5.15.5,<6.0.0)
Requires-Dist: biopython (>=1.79,<2.0)
Requires-Dist: ete3 (>=3.1.2,<4.0.0)
Requires-Dist: goatools (>=1.1.6,<2.0.0)
Requires-Dist: numpy (>=1.21.2,<2.0.0)
Requires-Dist: pandas (>=1.3.3,<2.0.0)
Requires-Dist: scipy (>=1.7.1,<2.0.0)
Project-URL: Repository, https://github.com/moshi4/FastDTLmapper/
